PrettyHTML/__init__.py
PrettyHTML/html_handler.py
PrettyHTML/utillites.py
prettyhtml-0.9.1.dist-info/METADATA
prettyhtml-0.9.1.dist-info/WHEEL
prettyhtml-0.9.1.dist-info/RECORD
