Metadata-Version: 2.1
Name: prettyhtml
Version: 0.9.1
Summary: This code can refactor your html in pretty dict
License: MIT
Author: dima-on
Author-email: sinica911@gmail.com
Requires-Python: >=3.12,<4.0
Classifier: License :: OSI Approved :: MIT License
Classifier: Programming Language :: Python :: 3
Classifier: Programming Language :: Python :: 3.12
Classifier: Programming Language :: Python :: 3.13
Requires-Dist: bs4 (>=0.0.2,<0.0.3)
